README.rst
setup.py
adhan/__init__.py
adhan/adhan.py
adhan/calculations.py
adhan/methods.py
adhan.egg-info/PKG-INFO
adhan.egg-info/SOURCES.txt
adhan.egg-info/dependency_links.txt
adhan.egg-info/pbr.json
adhan.egg-info/top_level.txt