Metadata-Version: 1.1
Name: adhan
Version: 0.1.1
Summary: Python library for computing adhan times
Home-page: https://github.com/hayalasalah/adhan.py
Author: Zuhair Parvez
Author-email: zuhairparvez@gmail.com
License: LGPL 3.0
Download-URL: https://github.com/hayalasalah/adhan.py/releases/tag/0.1
Keywords: adhan,islam,muslim,religious
Platform: UNKNOWN
Classifier: License :: OSI Approved :: GNU Lesser General Public License v3 (LGPLv3)
Classifier: Programming Language :: Python :: 2.7
Classifier: Programming Language :: Python :: 3.2
Classifier: Programming Language :: Python :: 3.3
Classifier: Programming Language :: Python :: 3.4
Classifier: Topic :: Religion
